annin_dofu/__init__.py
annin_dofu/_version.py
annin_dofu/calc.py
annin_dofu/matrix.py
annin_dofu/parallel.py
annin_dofu/stats.py
annin_dofu/utils.py
annin_dofu/response_surface_methodology/__init__.py
annin_dofu/response_surface_methodology/approximation_2d_function.py
annin_dofu/response_surface_methodology/approximation_rbf_interpolation.py
annin_dofu/stocking_quantity_optimization/__init__.py
annin_dofu/stocking_quantity_optimization/news_vendor_model.py
annin_dofu-0.0.3.dist-info/LICENSE
annin_dofu-0.0.3.dist-info/METADATA
annin_dofu-0.0.3.dist-info/WHEEL
annin_dofu-0.0.3.dist-info/top_level.txt
annin_dofu-0.0.3.dist-info/RECORD
