Metadata-Version: 2.1
Name: annin-dofu
Version: 0.0.3
Summary: annin_dofu description
Home-page: https://github.com/laplaciannin102/annin_dofu
Author: laplaciannin102(Kosuke Asada)
Author-email: laplaciannin102@gmail.com
License: BSD 2-Clause License        
License-File: LICENSE
Requires-Dist: joblib (>=1.1.0)
Requires-Dist: multiprocess (>=0.70.12.2)
Requires-Dist: numpy (>=1.21.2)
Requires-Dist: pandas (>=1.3.3)
Requires-Dist: scikit-learn (>=1.0)
Requires-Dist: scipy (>=1.7.1)
Requires-Dist: statsmodels (>=0.13.0)
